README.md
setup.py
xcache/__init__.py
xcache/xcache_impl.py
xcache_lib.egg-info/PKG-INFO
xcache_lib.egg-info/SOURCES.txt
xcache_lib.egg-info/dependency_links.txt
xcache_lib.egg-info/top_level.txt