Metadata-Version: 2.1
Name: xcache-lib
Version: 0.0.2
Summary: A simplest and thread-safe LRU cache, which support key-func, release-func and hit-stat.
Home-page: https://github.com/ChuanqiTan/xcache
Author: Chuanqi Tan
Author-email: chuanqi.tan@gmail.com
License: MIT
Keywords: thread safe cache,LRU cache,key function,release function,hit stat
Platform: UNKNOWN
